__init__.py
pandashift/__init__.py
pandashift/constants.py
pandashift/create_table_from_df.py
pandashift/load_df.py
pandashift/read_execute.py
pandashift-1.0.5.dist-info/METADATA
pandashift-1.0.5.dist-info/WHEEL
pandashift-1.0.5.dist-info/top_level.txt
pandashift-1.0.5.dist-info/RECORD
