Metadata-Version: 2.1
Name: pandashift
Version: 1.0.5
Summary: Module for quick and easy access to redshift using pandas
Author-email: Maksim Linichenko <maksim.linichenko@yahoo.com>
Project-URL: Homepage, https://github.com/tumax7/pandashift
Project-URL: Issues, https://github.com/tumax7/pandashift/issues
Keywords: redshift,pandas,analytics,amazon,pandashift
Classifier: Development Status :: 5 - Production/Stable
Classifier: Programming Language :: Python :: 3.10
Classifier: Programming Language :: Python :: 3.11
Classifier: Programming Language :: Python :: 3.12
Classifier: Programming Language :: Python :: 3
Classifier: Operating System :: OS Independent
Requires-Python: >=3.10
Requires-Dist: psycopg
Requires-Dist: psycopg[binary]
Requires-Dist: pandas
Requires-Dist: python-dotenv
Provides-Extra: dev
Requires-Dist: pytest; extra == "dev"
Requires-Dist: pylint; extra == "dev"
